{
  "type": "File",
  "start": 0,
  "end": 421,
  "loc": {
    "start": {
      "line": 1,
      "column": 0
    },
    "end": {
      "line": 22,
      "column": 0
    }
  },
  "program": {
    "type": "Program",
    "start": 0,
    "end": 421,
    "loc": {
      "start": {
        "line": 1,
        "column": 0
      },
      "end": {
        "line": 22,
        "column": 0
      }
    },
    "sourceType": "module",
    "body": [
      {
        "type": "ImportDeclaration",
        "start": 0,
        "end": 32,
        "loc": {
          "start": {
            "line": 1,
            "column": 0
          },
          "end": {
            "line": 1,
            "column": 32
          }
        },
        "specifiers": [
          {
            "type": "ImportDefaultSpecifier",
            "start": 7,
            "end": 14,
            "loc": {
              "start": {
                "line": 1,
                "column": 7
              },
              "end": {
                "line": 1,
                "column": 14
              }
            },
            "local": {
              "type": "Identifier",
              "start": 7,
              "end": 14,
              "loc": {
                "start": {
                  "line": 1,
                  "column": 7
                },
                "end": {
                  "line": 1,
                  "column": 14
                },
                "identifierName": "BaseApi"
              },
              "name": "BaseApi"
            }
          }
        ],
        "source": {
          "type": "StringLiteral",
          "start": 20,
          "end": 31,
          "loc": {
            "start": {
              "line": 1,
              "column": 20
            },
            "end": {
              "line": 1,
              "column": 31
            }
          },
          "extra": {
            "rawValue": "./baseApi",
            "raw": "\"./baseApi\""
          },
          "value": "./baseApi"
        }
      },
      {
        "type": "VariableDeclaration",
        "start": 34,
        "end": 79,
        "loc": {
          "start": {
            "line": 3,
            "column": 0
          },
          "end": {
            "line": 3,
            "column": 45
          }
        },
        "declarations": [
          {
            "type": "VariableDeclarator",
            "start": 40,
            "end": 78,
            "loc": {
              "start": {
                "line": 3,
                "column": 6
              },
              "end": {
                "line": 3,
                "column": 44
              }
            },
            "id": {
              "type": "Identifier",
              "start": 40,
              "end": 47,
              "loc": {
                "start": {
                  "line": 3,
                  "column": 6
                },
                "end": {
                  "line": 3,
                  "column": 13
                },
                "identifierName": "puppies"
              },
              "name": "puppies"
            },
            "init": {
              "type": "ArrayExpression",
              "start": 50,
              "end": 78,
              "loc": {
                "start": {
                  "line": 3,
                  "column": 16
                },
                "end": {
                  "line": 3,
                  "column": 44
                }
              },
              "elements": [
                {
                  "type": "StringLiteral",
                  "start": 51,
                  "end": 59,
                  "loc": {
                    "start": {
                      "line": 3,
                      "column": 17
                    },
                    "end": {
                      "line": 3,
                      "column": 25
                    }
                  },
                  "extra": {
                    "rawValue": "Fluffy",
                    "raw": "'Fluffy'"
                  },
                  "value": "Fluffy"
                },
                {
                  "type": "StringLiteral",
                  "start": 61,
                  "end": 68,
                  "loc": {
                    "start": {
                      "line": 3,
                      "column": 27
                    },
                    "end": {
                      "line": 3,
                      "column": 34
                    }
                  },
                  "extra": {
                    "rawValue": "Puffy",
                    "raw": "'Puffy'"
                  },
                  "value": "Puffy"
                },
                {
                  "type": "StringLiteral",
                  "start": 70,
                  "end": 77,
                  "loc": {
                    "start": {
                      "line": 3,
                      "column": 36
                    },
                    "end": {
                      "line": 3,
                      "column": 43
                    }
                  },
                  "extra": {
                    "rawValue": "Ruffy",
                    "raw": "'Ruffy'"
                  },
                  "value": "Ruffy"
                }
              ]
            }
          }
        ],
        "kind": "const",
        "trailingComments": [
          {
            "type": "CommentBlock",
            "value": "*\n * Just a fake api\n ",
            "start": 81,
            "end": 107,
            "loc": {
              "start": {
                "line": 5,
                "column": 0
              },
              "end": {
                "line": 7,
                "column": 3
              }
            }
          }
        ]
      },
      {
        "type": "Identifier",
        "start": 108,
        "end": 394,
        "loc": {
          "start": {
            "line": 8,
            "column": 0
          },
          "end": {
            "line": 19,
            "column": 1
          }
        },
        "id": {
          "type": "Identifier",
          "start": 114,
          "end": 122,
          "loc": {
            "start": {
              "line": 8,
              "column": 6
            },
            "end": {
              "line": 8,
              "column": 14
            },
            "identifierName": "PuppyApi"
          },
          "name": "PuppyApi",
          "leadingComments": null
        },
        "superClass": {
          "type": "Identifier",
          "start": 131,
          "end": 138,
          "loc": {
            "start": {
              "line": 8,
              "column": 23
            },
            "end": {
              "line": 8,
              "column": 30
            },
            "identifierName": "BaseApi"
          },
          "name": "BaseApi"
        },
        "body": {
          "type": "ClassBody",
          "start": 138,
          "end": 394,
          "loc": {
            "start": {
              "line": 8,
              "column": 30
            },
            "end": {
              "line": 19,
              "column": 1
            }
          },
          "body": [
            {
              "type": "ClassMethod",
              "start": 145,
              "end": 195,
              "loc": {
                "start": {
                  "line": 10,
                  "column": 4
                },
                "end": {
                  "line": 12,
                  "column": 5
                }
              },
              "static": false,
              "computed": false,
              "key": {
                "type": "Identifier",
                "start": 145,
                "end": 156,
                "loc": {
                  "start": {
                    "line": 10,
                    "column": 4
                  },
                  "end": {
                    "line": 10,
                    "column": 15
                  },
                  "identifierName": "constructor"
                },
                "name": "constructor"
              },
              "kind": "constructor",
              "id": null,
              "generator": false,
              "expression": false,
              "async": false,
              "params": [
                {
                  "type": "Identifier",
                  "start": 157,
                  "end": 164,
                  "loc": {
                    "start": {
                      "line": 10,
                      "column": 16
                    },
                    "end": {
                      "line": 10,
                      "column": 23
                    },
                    "identifierName": "baseUrl"
                  },
                  "name": "baseUrl"
                }
              ],
              "body": {
                "type": "BlockStatement",
                "start": 165,
                "end": 195,
                "loc": {
                  "start": {
                    "line": 10,
                    "column": 24
                  },
                  "end": {
                    "line": 12,
                    "column": 5
                  }
                },
                "body": [
                  {
                    "type": "ExpressionStatement",
                    "start": 175,
                    "end": 189,
                    "loc": {
                      "start": {
                        "line": 11,
                        "column": 8
                      },
                      "end": {
                        "line": 11,
                        "column": 22
                      }
                    },
                    "expression": {
                      "type": "CallExpression",
                      "start": 175,
                      "end": 189,
                      "loc": {
                        "start": {
                          "line": 11,
                          "column": 8
                        },
                        "end": {
                          "line": 11,
                          "column": 22
                        }
                      },
                      "callee": {
                        "type": "Super",
                        "start": 175,
                        "end": 180,
                        "loc": {
                          "start": {
                            "line": 11,
                            "column": 8
                          },
                          "end": {
                            "line": 11,
                            "column": 13
                          }
                        }
                      },
                      "arguments": [
                        {
                          "type": "Identifier",
                          "start": 181,
                          "end": 188,
                          "loc": {
                            "start": {
                              "line": 11,
                              "column": 14
                            },
                            "end": {
                              "line": 11,
                              "column": 21
                            },
                            "identifierName": "baseUrl"
                          },
                          "name": "baseUrl"
                        }
                      ]
                    }
                  }
                ],
                "directives": []
              }
            },
            {
              "type": "ClassMethod",
              "start": 201,
              "end": 392,
              "loc": {
                "start": {
                  "line": 14,
                  "column": 4
                },
                "end": {
                  "line": 18,
                  "column": 5
                }
              },
              "static": false,
              "computed": false,
              "key": {
                "type": "Identifier",
                "start": 207,
                "end": 220,
                "loc": {
                  "start": {
                    "line": 14,
                    "column": 10
                  },
                  "end": {
                    "line": 14,
                    "column": 23
                  },
                  "identifierName": "getAllPuppies"
                },
                "name": "getAllPuppies"
              },
              "kind": "method",
              "id": null,
              "generator": false,
              "expression": false,
              "async": true,
              "params": [],
              "body": {
                "type": "BlockStatement",
                "start": 223,
                "end": 392,
                "loc": {
                  "start": {
                    "line": 14,
                    "column": 26
                  },
                  "end": {
                    "line": 18,
                    "column": 5
                  }
                },
                "body": [
                  {
                    "type": "VariableDeclaration",
                    "start": 233,
                    "end": 286,
                    "loc": {
                      "start": {
                        "line": 15,
                        "column": 8
                      },
                      "end": {
                        "line": 15,
                        "column": 61
                      }
                    },
                    "declarations": [
                      {
                        "type": "VariableDeclarator",
                        "start": 239,
                        "end": 285,
                        "loc": {
                          "start": {
                            "line": 15,
                            "column": 14
                          },
                          "end": {
                            "line": 15,
                            "column": 60
                          }
                        },
                        "id": {
                          "type": "Identifier",
                          "start": 239,
                          "end": 251,
                          "loc": {
                            "start": {
                              "line": 15,
                              "column": 14
                            },
                            "end": {
                              "line": 15,
                              "column": 26
                            },
                            "identifierName": "httpResponse"
                          },
                          "name": "httpResponse"
                        },
                        "init": {
                          "type": "AwaitExpression",
                          "start": 254,
                          "end": 285,
                          "loc": {
                            "start": {
                              "line": 15,
                              "column": 29
                            },
                            "end": {
                              "line": 15,
                              "column": 60
                            }
                          },
                          "argument": {
                            "type": "CallExpression",
                            "start": 260,
                            "end": 285,
                            "loc": {
                              "start": {
                                "line": 15,
                                "column": 35
                              },
                              "end": {
                                "line": 15,
                                "column": 60
                              }
                            },
                            "callee": {
                              "type": "MemberExpression",
                              "start": 260,
                              "end": 273,
                              "loc": {
                                "start": {
                                  "line": 15,
                                  "column": 35
                                },
                                "end": {
                                  "line": 15,
                                  "column": 48
                                }
                              },
                              "object": {
                                "type": "MemberExpression",
                                "start": 260,
                                "end": 269,
                                "loc": {
                                  "start": {
                                    "line": 15,
                                    "column": 35
                                  },
                                  "end": {
                                    "line": 15,
                                    "column": 44
                                  }
                                },
                                "object": {
                                  "type": "ThisExpression",
                                  "start": 260,
                                  "end": 264,
                                  "loc": {
                                    "start": {
                                      "line": 15,
                                      "column": 35
                                    },
                                    "end": {
                                      "line": 15,
                                      "column": 39
                                    }
                                  }
                                },
                                "property": {
                                  "type": "Identifier",
                                  "start": 265,
                                  "end": 269,
                                  "loc": {
                                    "start": {
                                      "line": 15,
                                      "column": 40
                                    },
                                    "end": {
                                      "line": 15,
                                      "column": 44
                                    },
                                    "identifierName": "http"
                                  },
                                  "name": "http"
                                },
                                "computed": false
                              },
                              "property": {
                                "type": "Identifier",
                                "start": 270,
                                "end": 273,
                                "loc": {
                                  "start": {
                                    "line": 15,
                                    "column": 45
                                  },
                                  "end": {
                                    "line": 15,
                                    "column": 48
                                  },
                                  "identifierName": "get"
                                },
                                "name": "get"
                              },
                              "computed": false
                            },
                            "arguments": [
                              {
                                "type": "StringLiteral",
                                "start": 274,
                                "end": 284,
                                "loc": {
                                  "start": {
                                    "line": 15,
                                    "column": 49
                                  },
                                  "end": {
                                    "line": 15,
                                    "column": 59
                                  }
                                },
                                "extra": {
                                  "rawValue": "/puppies",
                                  "raw": "'/puppies'"
                                },
                                "value": "/puppies"
                              }
                            ]
                          }
                        }
                      }
                    ],
                    "kind": "const"
                  },
                  {
                    "type": "IfStatement",
                    "start": 295,
                    "end": 348,
                    "loc": {
                      "start": {
                        "line": 16,
                        "column": 8
                      },
                      "end": {
                        "line": 16,
                        "column": 61
                      }
                    },
                    "test": {
                      "type": "CallExpression",
                      "start": 298,
                      "end": 321,
                      "loc": {
                        "start": {
                          "line": 16,
                          "column": 11
                        },
                        "end": {
                          "line": 16,
                          "column": 34
                        }
                      },
                      "callee": {
                        "type": "MemberExpression",
                        "start": 298,
                        "end": 319,
                        "loc": {
                          "start": {
                            "line": 16,
                            "column": 11
                          },
                          "end": {
                            "line": 16,
                            "column": 32
                          }
                        },
                        "object": {
                          "type": "Identifier",
                          "start": 298,
                          "end": 310,
                          "loc": {
                            "start": {
                              "line": 16,
                              "column": 11
                            },
                            "end": {
                              "line": 16,
                              "column": 23
                            },
                            "identifierName": "httpResponse"
                          },
                          "name": "httpResponse"
                        },
                        "property": {
                          "type": "Identifier",
                          "start": 311,
                          "end": 319,
                          "loc": {
                            "start": {
                              "line": 16,
                              "column": 24
                            },
                            "end": {
                              "line": 16,
                              "column": 32
                            },
                            "identifierName": "hasError"
                          },
                          "name": "hasError"
                        },
                        "computed": false
                      },
                      "arguments": []
                    },
                    "consequent": {
                      "type": "ThrowStatement",
                      "start": 323,
                      "end": 348,
                      "loc": {
                        "start": {
                          "line": 16,
                          "column": 36
                        },
                        "end": {
                          "line": 16,
                          "column": 61
                        }
                      },
                      "argument": {
                        "type": "MemberExpression",
                        "start": 329,
                        "end": 347,
                        "loc": {
                          "start": {
                            "line": 16,
                            "column": 42
                          },
                          "end": {
                            "line": 16,
                            "column": 60
                          }
                        },
                        "object": {
                          "type": "Identifier",
                          "start": 329,
                          "end": 341,
                          "loc": {
                            "start": {
                              "line": 16,
                              "column": 42
                            },
                            "end": {
                              "line": 16,
                              "column": 54
                            },
                            "identifierName": "httpResponse"
                          },
                          "name": "httpResponse"
                        },
                        "property": {
                          "type": "Identifier",
                          "start": 342,
                          "end": 347,
                          "loc": {
                            "start": {
                              "line": 16,
                              "column": 55
                            },
                            "end": {
                              "line": 16,
                              "column": 60
                            },
                            "identifierName": "error"
                          },
                          "name": "error"
                        },
                        "computed": false
                      }
                    },
                    "alternate": null
                  },
                  {
                    "type": "ReturnStatement",
                    "start": 357,
                    "end": 386,
                    "loc": {
                      "start": {
                        "line": 17,
                        "column": 8
                      },
                      "end": {
                        "line": 17,
                        "column": 37
                      }
                    },
                    "argument": {
                      "type": "MemberExpression",
                      "start": 364,
                      "end": 385,
                      "loc": {
                        "start": {
                          "line": 17,
                          "column": 15
                        },
                        "end": {
                          "line": 17,
                          "column": 36
                        }
                      },
                      "object": {
                        "type": "Identifier",
                        "start": 364,
                        "end": 376,
                        "loc": {
                          "start": {
                            "line": 17,
                            "column": 15
                          },
                          "end": {
                            "line": 17,
                            "column": 27
                          },
                          "identifierName": "httpResponse"
                        },
                        "name": "httpResponse"
                      },
                      "property": {
                        "type": "Identifier",
                        "start": 377,
                        "end": 385,
                        "loc": {
                          "start": {
                            "line": 17,
                            "column": 28
                          },
                          "end": {
                            "line": 17,
                            "column": 36
                          },
                          "identifierName": "response"
                        },
                        "name": "response"
                      },
                      "computed": false
                    }
                  }
                ],
                "directives": []
              }
            }
          ]
        },
        "leadingComments": [],
        "name": "_",
        "trailingComments": []
      },
      {
        "type": "Identifier",
        "start": 396,
        "end": 420,
        "loc": {
          "start": {
            "line": 21,
            "column": 0
          },
          "end": {
            "line": 21,
            "column": 24
          }
        },
        "declaration": {
          "type": "Identifier",
          "start": 411,
          "end": 419,
          "loc": {
            "start": {
              "line": 21,
              "column": 15
            },
            "end": {
              "line": 21,
              "column": 23
            },
            "identifierName": "PuppyApi"
          },
          "name": "PuppyApi"
        },
        "name": "_",
        "leadingComments": [],
        "trailingComments": []
      },
      {
        "type": "ExportDefaultDeclaration",
        "start": 396,
        "end": 420,
        "loc": {
          "start": {
            "line": 21,
            "column": 0
          },
          "end": {
            "line": 21,
            "column": 24
          }
        },
        "declaration": {
          "type": "ClassDeclaration",
          "start": 108,
          "end": 394,
          "loc": {
            "start": {
              "line": 8,
              "column": 0
            },
            "end": {
              "line": 19,
              "column": 1
            }
          },
          "id": {
            "type": "Identifier",
            "start": 114,
            "end": 122,
            "loc": {
              "start": {
                "line": 8,
                "column": 6
              },
              "end": {
                "line": 8,
                "column": 14
              },
              "identifierName": "PuppyApi"
            },
            "name": "PuppyApi",
            "leadingComments": null
          },
          "superClass": {
            "type": "Identifier",
            "start": 131,
            "end": 138,
            "loc": {
              "start": {
                "line": 8,
                "column": 23
              },
              "end": {
                "line": 8,
                "column": 30
              },
              "identifierName": "BaseApi"
            },
            "name": "BaseApi"
          },
          "body": {
            "type": "ClassBody",
            "start": 138,
            "end": 394,
            "loc": {
              "start": {
                "line": 8,
                "column": 30
              },
              "end": {
                "line": 19,
                "column": 1
              }
            },
            "body": [
              {
                "type": "ClassMethod",
                "start": 145,
                "end": 195,
                "loc": {
                  "start": {
                    "line": 10,
                    "column": 4
                  },
                  "end": {
                    "line": 12,
                    "column": 5
                  }
                },
                "static": false,
                "computed": false,
                "key": {
                  "type": "Identifier",
                  "start": 145,
                  "end": 156,
                  "loc": {
                    "start": {
                      "line": 10,
                      "column": 4
                    },
                    "end": {
                      "line": 10,
                      "column": 15
                    },
                    "identifierName": "constructor"
                  },
                  "name": "constructor"
                },
                "kind": "constructor",
                "id": null,
                "generator": false,
                "expression": false,
                "async": false,
                "params": [
                  {
                    "type": "Identifier",
                    "start": 157,
                    "end": 164,
                    "loc": {
                      "start": {
                        "line": 10,
                        "column": 16
                      },
                      "end": {
                        "line": 10,
                        "column": 23
                      },
                      "identifierName": "baseUrl"
                    },
                    "name": "baseUrl"
                  }
                ],
                "body": {
                  "type": "BlockStatement",
                  "start": 165,
                  "end": 195,
                  "loc": {
                    "start": {
                      "line": 10,
                      "column": 24
                    },
                    "end": {
                      "line": 12,
                      "column": 5
                    }
                  },
                  "body": [
                    {
                      "type": "ExpressionStatement",
                      "start": 175,
                      "end": 189,
                      "loc": {
                        "start": {
                          "line": 11,
                          "column": 8
                        },
                        "end": {
                          "line": 11,
                          "column": 22
                        }
                      },
                      "expression": {
                        "type": "CallExpression",
                        "start": 175,
                        "end": 189,
                        "loc": {
                          "start": {
                            "line": 11,
                            "column": 8
                          },
                          "end": {
                            "line": 11,
                            "column": 22
                          }
                        },
                        "callee": {
                          "type": "Super",
                          "start": 175,
                          "end": 180,
                          "loc": {
                            "start": {
                              "line": 11,
                              "column": 8
                            },
                            "end": {
                              "line": 11,
                              "column": 13
                            }
                          }
                        },
                        "arguments": [
                          {
                            "type": "Identifier",
                            "start": 181,
                            "end": 188,
                            "loc": {
                              "start": {
                                "line": 11,
                                "column": 14
                              },
                              "end": {
                                "line": 11,
                                "column": 21
                              },
                              "identifierName": "baseUrl"
                            },
                            "name": "baseUrl"
                          }
                        ]
                      }
                    }
                  ],
                  "directives": []
                }
              },
              {
                "type": "ClassMethod",
                "start": 201,
                "end": 392,
                "loc": {
                  "start": {
                    "line": 14,
                    "column": 4
                  },
                  "end": {
                    "line": 18,
                    "column": 5
                  }
                },
                "static": false,
                "computed": false,
                "key": {
                  "type": "Identifier",
                  "start": 207,
                  "end": 220,
                  "loc": {
                    "start": {
                      "line": 14,
                      "column": 10
                    },
                    "end": {
                      "line": 14,
                      "column": 23
                    },
                    "identifierName": "getAllPuppies"
                  },
                  "name": "getAllPuppies"
                },
                "kind": "method",
                "id": null,
                "generator": false,
                "expression": false,
                "async": true,
                "params": [],
                "body": {
                  "type": "BlockStatement",
                  "start": 223,
                  "end": 392,
                  "loc": {
                    "start": {
                      "line": 14,
                      "column": 26
                    },
                    "end": {
                      "line": 18,
                      "column": 5
                    }
                  },
                  "body": [
                    {
                      "type": "VariableDeclaration",
                      "start": 233,
                      "end": 286,
                      "loc": {
                        "start": {
                          "line": 15,
                          "column": 8
                        },
                        "end": {
                          "line": 15,
                          "column": 61
                        }
                      },
                      "declarations": [
                        {
                          "type": "VariableDeclarator",
                          "start": 239,
                          "end": 285,
                          "loc": {
                            "start": {
                              "line": 15,
                              "column": 14
                            },
                            "end": {
                              "line": 15,
                              "column": 60
                            }
                          },
                          "id": {
                            "type": "Identifier",
                            "start": 239,
                            "end": 251,
                            "loc": {
                              "start": {
                                "line": 15,
                                "column": 14
                              },
                              "end": {
                                "line": 15,
                                "column": 26
                              },
                              "identifierName": "httpResponse"
                            },
                            "name": "httpResponse"
                          },
                          "init": {
                            "type": "AwaitExpression",
                            "start": 254,
                            "end": 285,
                            "loc": {
                              "start": {
                                "line": 15,
                                "column": 29
                              },
                              "end": {
                                "line": 15,
                                "column": 60
                              }
                            },
                            "argument": {
                              "type": "CallExpression",
                              "start": 260,
                              "end": 285,
                              "loc": {
                                "start": {
                                  "line": 15,
                                  "column": 35
                                },
                                "end": {
                                  "line": 15,
                                  "column": 60
                                }
                              },
                              "callee": {
                                "type": "MemberExpression",
                                "start": 260,
                                "end": 273,
                                "loc": {
                                  "start": {
                                    "line": 15,
                                    "column": 35
                                  },
                                  "end": {
                                    "line": 15,
                                    "column": 48
                                  }
                                },
                                "object": {
                                  "type": "MemberExpression",
                                  "start": 260,
                                  "end": 269,
                                  "loc": {
                                    "start": {
                                      "line": 15,
                                      "column": 35
                                    },
                                    "end": {
                                      "line": 15,
                                      "column": 44
                                    }
                                  },
                                  "object": {
                                    "type": "ThisExpression",
                                    "start": 260,
                                    "end": 264,
                                    "loc": {
                                      "start": {
                                        "line": 15,
                                        "column": 35
                                      },
                                      "end": {
                                        "line": 15,
                                        "column": 39
                                      }
                                    }
                                  },
                                  "property": {
                                    "type": "Identifier",
                                    "start": 265,
                                    "end": 269,
                                    "loc": {
                                      "start": {
                                        "line": 15,
                                        "column": 40
                                      },
                                      "end": {
                                        "line": 15,
                                        "column": 44
                                      },
                                      "identifierName": "http"
                                    },
                                    "name": "http"
                                  },
                                  "computed": false
                                },
                                "property": {
                                  "type": "Identifier",
                                  "start": 270,
                                  "end": 273,
                                  "loc": {
                                    "start": {
                                      "line": 15,
                                      "column": 45
                                    },
                                    "end": {
                                      "line": 15,
                                      "column": 48
                                    },
                                    "identifierName": "get"
                                  },
                                  "name": "get"
                                },
                                "computed": false
                              },
                              "arguments": [
                                {
                                  "type": "StringLiteral",
                                  "start": 274,
                                  "end": 284,
                                  "loc": {
                                    "start": {
                                      "line": 15,
                                      "column": 49
                                    },
                                    "end": {
                                      "line": 15,
                                      "column": 59
                                    }
                                  },
                                  "extra": {
                                    "rawValue": "/puppies",
                                    "raw": "'/puppies'"
                                  },
                                  "value": "/puppies"
                                }
                              ]
                            }
                          }
                        }
                      ],
                      "kind": "const"
                    },
                    {
                      "type": "IfStatement",
                      "start": 295,
                      "end": 348,
                      "loc": {
                        "start": {
                          "line": 16,
                          "column": 8
                        },
                        "end": {
                          "line": 16,
                          "column": 61
                        }
                      },
                      "test": {
                        "type": "CallExpression",
                        "start": 298,
                        "end": 321,
                        "loc": {
                          "start": {
                            "line": 16,
                            "column": 11
                          },
                          "end": {
                            "line": 16,
                            "column": 34
                          }
                        },
                        "callee": {
                          "type": "MemberExpression",
                          "start": 298,
                          "end": 319,
                          "loc": {
                            "start": {
                              "line": 16,
                              "column": 11
                            },
                            "end": {
                              "line": 16,
                              "column": 32
                            }
                          },
                          "object": {
                            "type": "Identifier",
                            "start": 298,
                            "end": 310,
                            "loc": {
                              "start": {
                                "line": 16,
                                "column": 11
                              },
                              "end": {
                                "line": 16,
                                "column": 23
                              },
                              "identifierName": "httpResponse"
                            },
                            "name": "httpResponse"
                          },
                          "property": {
                            "type": "Identifier",
                            "start": 311,
                            "end": 319,
                            "loc": {
                              "start": {
                                "line": 16,
                                "column": 24
                              },
                              "end": {
                                "line": 16,
                                "column": 32
                              },
                              "identifierName": "hasError"
                            },
                            "name": "hasError"
                          },
                          "computed": false
                        },
                        "arguments": []
                      },
                      "consequent": {
                        "type": "ThrowStatement",
                        "start": 323,
                        "end": 348,
                        "loc": {
                          "start": {
                            "line": 16,
                            "column": 36
                          },
                          "end": {
                            "line": 16,
                            "column": 61
                          }
                        },
                        "argument": {
                          "type": "MemberExpression",
                          "start": 329,
                          "end": 347,
                          "loc": {
                            "start": {
                              "line": 16,
                              "column": 42
                            },
                            "end": {
                              "line": 16,
                              "column": 60
                            }
                          },
                          "object": {
                            "type": "Identifier",
                            "start": 329,
                            "end": 341,
                            "loc": {
                              "start": {
                                "line": 16,
                                "column": 42
                              },
                              "end": {
                                "line": 16,
                                "column": 54
                              },
                              "identifierName": "httpResponse"
                            },
                            "name": "httpResponse"
                          },
                          "property": {
                            "type": "Identifier",
                            "start": 342,
                            "end": 347,
                            "loc": {
                              "start": {
                                "line": 16,
                                "column": 55
                              },
                              "end": {
                                "line": 16,
                                "column": 60
                              },
                              "identifierName": "error"
                            },
                            "name": "error"
                          },
                          "computed": false
                        }
                      },
                      "alternate": null
                    },
                    {
                      "type": "ReturnStatement",
                      "start": 357,
                      "end": 386,
                      "loc": {
                        "start": {
                          "line": 17,
                          "column": 8
                        },
                        "end": {
                          "line": 17,
                          "column": 37
                        }
                      },
                      "argument": {
                        "type": "MemberExpression",
                        "start": 364,
                        "end": 385,
                        "loc": {
                          "start": {
                            "line": 17,
                            "column": 15
                          },
                          "end": {
                            "line": 17,
                            "column": 36
                          }
                        },
                        "object": {
                          "type": "Identifier",
                          "start": 364,
                          "end": 376,
                          "loc": {
                            "start": {
                              "line": 17,
                              "column": 15
                            },
                            "end": {
                              "line": 17,
                              "column": 27
                            },
                            "identifierName": "httpResponse"
                          },
                          "name": "httpResponse"
                        },
                        "property": {
                          "type": "Identifier",
                          "start": 377,
                          "end": 385,
                          "loc": {
                            "start": {
                              "line": 17,
                              "column": 28
                            },
                            "end": {
                              "line": 17,
                              "column": 36
                            },
                            "identifierName": "response"
                          },
                          "name": "response"
                        },
                        "computed": false
                      }
                    }
                  ],
                  "directives": []
                }
              }
            ]
          },
          "leadingComments": [
            {
              "type": "CommentBlock",
              "value": "*\n * Just a fake api\n ",
              "start": 81,
              "end": 107,
              "loc": {
                "start": {
                  "line": 5,
                  "column": 0
                },
                "end": {
                  "line": 7,
                  "column": 3
                }
              }
            }
          ],
          "__PseudoExport__": false,
          "trailingComments": []
        },
        "leadingComments": null
      }
    ],
    "directives": []
  },
  "comments": [
    {
      "type": "CommentBlock",
      "value": "*\n * Just a fake api\n ",
      "start": 81,
      "end": 107,
      "loc": {
        "start": {
          "line": 5,
          "column": 0
        },
        "end": {
          "line": 7,
          "column": 3
        }
      }
    }
  ],
  "tokens": [
    {
      "type": {
        "label": "import",
        "keyword": "import",
        "beforeExpr": false,
        "startsExpr": true,
        "rightAssociative": false,
        "isLoop": false,
        "isAssign": false,
        "prefix": false,
        "postfix": false,
        "binop": null,
        "updateContext": null
      },
      "value": "import",
      "start": 0,
      "end": 6,
      "loc": {
        "start": {
          "line": 1,
          "column": 0
        },
        "end": {
          "line": 1,
          "column": 6
        }
      }
    },
    {
      "type": {
        "label": "name",
        "beforeExpr": false,
        "startsExpr": true,
        "rightAssociative": false,
        "isLoop": false,
        "isAssign": false,
        "prefix": false,
        "postfix": false,
        "binop": null
      },
      "value": "BaseApi",
      "start": 7,
      "end": 14,
      "loc": {
        "start": {
          "line": 1,
          "column": 7
        },
        "end": {
          "line": 1,
          "column": 14
        }
      }
    },
    {
      "type": {
        "label": "name",
        "beforeExpr": false,
        "startsExpr": true,
        "rightAssociative": false,
        "isLoop": false,
        "isAssign": false,
        "prefix": false,
        "postfix": false,
        "binop": null
      },
      "value": "from",
      "start": 15,
      "end": 19,
      "loc": {
        "start": {
          "line": 1,
          "column": 15
        },
        "end": {
          "line": 1,
          "column": 19
        }
      }
    },
    {
      "type": {
        "label": "string",
        "beforeExpr": false,
        "startsExpr": true,
        "rightAssociative": false,
        "isLoop": false,
        "isAssign": false,
        "prefix": false,
        "postfix": false,
        "binop": null,
        "updateContext": null
      },
      "value": "./baseApi",
      "start": 20,
      "end": 31,
      "loc": {
        "start": {
          "line": 1,
          "column": 20
        },
        "end": {
          "line": 1,
          "column": 31
        }
      }
    },
    {
      "type": {
        "label": ";",
        "beforeExpr": true,
        "startsExpr": false,
        "rightAssociative": false,
        "isLoop": false,
        "isAssign": false,
        "prefix": false,
        "postfix": false,
        "binop": null,
        "updateContext": null
      },
      "start": 31,
      "end": 32,
      "loc": {
        "start": {
          "line": 1,
          "column": 31
        },
        "end": {
          "line": 1,
          "column": 32
        }
      }
    },
    {
      "type": {
        "label": "const",
        "keyword": "const",
        "beforeExpr": false,
        "startsExpr": false,
        "rightAssociative": false,
        "isLoop": false,
        "isAssign": false,
        "prefix": false,
        "postfix": false,
        "binop": null,
        "updateContext": null
      },
      "value": "const",
      "start": 34,
      "end": 39,
      "loc": {
        "start": {
          "line": 3,
          "column": 0
        },
        "end": {
          "line": 3,
          "column": 5
        }
      }
    },
    {
      "type": {
        "label": "name",
        "beforeExpr": false,
        "startsExpr": true,
        "rightAssociative": false,
        "isLoop": false,
        "isAssign": false,
        "prefix": false,
        "postfix": false,
        "binop": null
      },
      "value": "puppies",
      "start": 40,
      "end": 47,
      "loc": {
        "start": {
          "line": 3,
          "column": 6
        },
        "end": {
          "line": 3,
          "column": 13
        }
      }
    },
    {
      "type": {
        "label": "=",
        "beforeExpr": true,
        "startsExpr": false,
        "rightAssociative": false,
        "isLoop": false,
        "isAssign": true,
        "prefix": false,
        "postfix": false,
        "binop": null,
        "updateContext": null
      },
      "value": "=",
      "start": 48,
      "end": 49,
      "loc": {
        "start": {
          "line": 3,
          "column": 14
        },
        "end": {
          "line": 3,
          "column": 15
        }
      }
    },
    {
      "type": {
        "label": "[",
        "beforeExpr": true,
        "startsExpr": true,
        "rightAssociative": false,
        "isLoop": false,
        "isAssign": false,
        "prefix": false,
        "postfix": false,
        "binop": null,
        "updateContext": null
      },
      "start": 50,
      "end": 51,
      "loc": {
        "start": {
          "line": 3,
          "column": 16
        },
        "end": {
          "line": 3,
          "column": 17
        }
      }
    },
    {
      "type": {
        "label": "string",
        "beforeExpr": false,
        "startsExpr": true,
        "rightAssociative": false,
        "isLoop": false,
        "isAssign": false,
        "prefix": false,
        "postfix": false,
        "binop": null,
        "updateContext": null
      },
      "value": "Fluffy",
      "start": 51,
      "end": 59,
      "loc": {
        "start": {
          "line": 3,
          "column": 17
        },
        "end": {
          "line": 3,
          "column": 25
        }
      }
    },
    {
      "type": {
        "label": ",",
        "beforeExpr": true,
        "startsExpr": false,
        "rightAssociative": false,
        "isLoop": false,
        "isAssign": false,
        "prefix": false,
        "postfix": false,
        "binop": null,
        "updateContext": null
      },
      "start": 59,
      "end": 60,
      "loc": {
        "start": {
          "line": 3,
          "column": 25
        },
        "end": {
          "line": 3,
          "column": 26
        }
      }
    },
    {
      "type": {
        "label": "string",
        "beforeExpr": false,
        "startsExpr": true,
        "rightAssociative": false,
        "isLoop": false,
        "isAssign": false,
        "prefix": false,
        "postfix": false,
        "binop": null,
        "updateContext": null
      },
      "value": "Puffy",
      "start": 61,
      "end": 68,
      "loc": {
        "start": {
          "line": 3,
          "column": 27
        },
        "end": {
          "line": 3,
          "column": 34
        }
      }
    },
    {
      "type": {
        "label": ",",
        "beforeExpr": true,
        "startsExpr": false,
        "rightAssociative": false,
        "isLoop": false,
        "isAssign": false,
        "prefix": false,
        "postfix": false,
        "binop": null,
        "updateContext": null
      },
      "start": 68,
      "end": 69,
      "loc": {
        "start": {
          "line": 3,
          "column": 34
        },
        "end": {
          "line": 3,
          "column": 35
        }
      }
    },
    {
      "type": {
        "label": "string",
        "beforeExpr": false,
        "startsExpr": true,
        "rightAssociative": false,
        "isLoop": false,
        "isAssign": false,
        "prefix": false,
        "postfix": false,
        "binop": null,
        "updateContext": null
      },
      "value": "Ruffy",
      "start": 70,
      "end": 77,
      "loc": {
        "start": {
          "line": 3,
          "column": 36
        },
        "end": {
          "line": 3,
          "column": 43
        }
      }
    },
    {
      "type": {
        "label": "]",
        "beforeExpr": false,
        "startsExpr": false,
        "rightAssociative": false,
        "isLoop": false,
        "isAssign": false,
        "prefix": false,
        "postfix": false,
        "binop": null,
        "updateContext": null
      },
      "start": 77,
      "end": 78,
      "loc": {
        "start": {
          "line": 3,
          "column": 43
        },
        "end": {
          "line": 3,
          "column": 44
        }
      }
    },
    {
      "type": {
        "label": ";",
        "beforeExpr": true,
        "startsExpr": false,
        "rightAssociative": false,
        "isLoop": false,
        "isAssign": false,
        "prefix": false,
        "postfix": false,
        "binop": null,
        "updateContext": null
      },
      "start": 78,
      "end": 79,
      "loc": {
        "start": {
          "line": 3,
          "column": 44
        },
        "end": {
          "line": 3,
          "column": 45
        }
      }
    },
    {
      "type": "CommentBlock",
      "value": "*\n * Just a fake api\n ",
      "start": 81,
      "end": 107,
      "loc": {
        "start": {
          "line": 5,
          "column": 0
        },
        "end": {
          "line": 7,
          "column": 3
        }
      }
    },
    {
      "type": {
        "label": "class",
        "keyword": "class",
        "beforeExpr": false,
        "startsExpr": false,
        "rightAssociative": false,
        "isLoop": false,
        "isAssign": false,
        "prefix": false,
        "postfix": false,
        "binop": null,
        "updateContext": null
      },
      "value": "class",
      "start": 108,
      "end": 113,
      "loc": {
        "start": {
          "line": 8,
          "column": 0
        },
        "end": {
          "line": 8,
          "column": 5
        }
      }
    },
    {
      "type": {
        "label": "name",
        "beforeExpr": false,
        "startsExpr": true,
        "rightAssociative": false,
        "isLoop": false,
        "isAssign": false,
        "prefix": false,
        "postfix": false,
        "binop": null
      },
      "value": "PuppyApi",
      "start": 114,
      "end": 122,
      "loc": {
        "start": {
          "line": 8,
          "column": 6
        },
        "end": {
          "line": 8,
          "column": 14
        }
      }
    },
    {
      "type": {
        "label": "extends",
        "keyword": "extends",
        "beforeExpr": true,
        "startsExpr": false,
        "rightAssociative": false,
        "isLoop": false,
        "isAssign": false,
        "prefix": false,
        "postfix": false,
        "binop": null,
        "updateContext": null
      },
      "value": "extends",
      "start": 123,
      "end": 130,
      "loc": {
        "start": {
          "line": 8,
          "column": 15
        },
        "end": {
          "line": 8,
          "column": 22
        }
      }
    },
    {
      "type": {
        "label": "name",
        "beforeExpr": false,
        "startsExpr": true,
        "rightAssociative": false,
        "isLoop": false,
        "isAssign": false,
        "prefix": false,
        "postfix": false,
        "binop": null
      },
      "value": "BaseApi",
      "start": 131,
      "end": 138,
      "loc": {
        "start": {
          "line": 8,
          "column": 23
        },
        "end": {
          "line": 8,
          "column": 30
        }
      }
    },
    {
      "type": {
        "label": "{",
        "beforeExpr": true,
        "startsExpr": true,
        "rightAssociative": false,
        "isLoop": false,
        "isAssign": false,
        "prefix": false,
        "postfix": false,
        "binop": null
      },
      "start": 138,
      "end": 139,
      "loc": {
        "start": {
          "line": 8,
          "column": 30
        },
        "end": {
          "line": 8,
          "column": 31
        }
      }
    },
    {
      "type": {
        "label": "name",
        "beforeExpr": false,
        "startsExpr": true,
        "rightAssociative": false,
        "isLoop": false,
        "isAssign": false,
        "prefix": false,
        "postfix": false,
        "binop": null
      },
      "value": "constructor",
      "start": 145,
      "end": 156,
      "loc": {
        "start": {
          "line": 10,
          "column": 4
        },
        "end": {
          "line": 10,
          "column": 15
        }
      }
    },
    {
      "type": {
        "label": "(",
        "beforeExpr": true,
        "startsExpr": true,
        "rightAssociative": false,
        "isLoop": false,
        "isAssign": false,
        "prefix": false,
        "postfix": false,
        "binop": null
      },
      "start": 156,
      "end": 157,
      "loc": {
        "start": {
          "line": 10,
          "column": 15
        },
        "end": {
          "line": 10,
          "column": 16
        }
      }
    },
    {
      "type": {
        "label": "name",
        "beforeExpr": false,
        "startsExpr": true,
        "rightAssociative": false,
        "isLoop": false,
        "isAssign": false,
        "prefix": false,
        "postfix": false,
        "binop": null
      },
      "value": "baseUrl",
      "start": 157,
      "end": 164,
      "loc": {
        "start": {
          "line": 10,
          "column": 16
        },
        "end": {
          "line": 10,
          "column": 23
        }
      }
    },
    {
      "type": {
        "label": ")",
        "beforeExpr": false,
        "startsExpr": false,
        "rightAssociative": false,
        "isLoop": false,
        "isAssign": false,
        "prefix": false,
        "postfix": false,
        "binop": null
      },
      "start": 164,
      "end": 165,
      "loc": {
        "start": {
          "line": 10,
          "column": 23
        },
        "end": {
          "line": 10,
          "column": 24
        }
      }
    },
    {
      "type": {
        "label": "{",
        "beforeExpr": true,
        "startsExpr": true,
        "rightAssociative": false,
        "isLoop": false,
        "isAssign": false,
        "prefix": false,
        "postfix": false,
        "binop": null
      },
      "start": 165,
      "end": 166,
      "loc": {
        "start": {
          "line": 10,
          "column": 24
        },
        "end": {
          "line": 10,
          "column": 25
        }
      }
    },
    {
      "type": {
        "label": "super",
        "keyword": "super",
        "beforeExpr": false,
        "startsExpr": true,
        "rightAssociative": false,
        "isLoop": false,
        "isAssign": false,
        "prefix": false,
        "postfix": false,
        "binop": null,
        "updateContext": null
      },
      "value": "super",
      "start": 175,
      "end": 180,
      "loc": {
        "start": {
          "line": 11,
          "column": 8
        },
        "end": {
          "line": 11,
          "column": 13
        }
      }
    },
    {
      "type": {
        "label": "(",
        "beforeExpr": true,
        "startsExpr": true,
        "rightAssociative": false,
        "isLoop": false,
        "isAssign": false,
        "prefix": false,
        "postfix": false,
        "binop": null
      },
      "start": 180,
      "end": 181,
      "loc": {
        "start": {
          "line": 11,
          "column": 13
        },
        "end": {
          "line": 11,
          "column": 14
        }
      }
    },
    {
      "type": {
        "label": "name",
        "beforeExpr": false,
        "startsExpr": true,
        "rightAssociative": false,
        "isLoop": false,
        "isAssign": false,
        "prefix": false,
        "postfix": false,
        "binop": null
      },
      "value": "baseUrl",
      "start": 181,
      "end": 188,
      "loc": {
        "start": {
          "line": 11,
          "column": 14
        },
        "end": {
          "line": 11,
          "column": 21
        }
      }
    },
    {
      "type": {
        "label": ")",
        "beforeExpr": false,
        "startsExpr": false,
        "rightAssociative": false,
        "isLoop": false,
        "isAssign": false,
        "prefix": false,
        "postfix": false,
        "binop": null
      },
      "start": 188,
      "end": 189,
      "loc": {
        "start": {
          "line": 11,
          "column": 21
        },
        "end": {
          "line": 11,
          "column": 22
        }
      }
    },
    {
      "type": {
        "label": "}",
        "beforeExpr": false,
        "startsExpr": false,
        "rightAssociative": false,
        "isLoop": false,
        "isAssign": false,
        "prefix": false,
        "postfix": false,
        "binop": null
      },
      "start": 194,
      "end": 195,
      "loc": {
        "start": {
          "line": 12,
          "column": 4
        },
        "end": {
          "line": 12,
          "column": 5
        }
      }
    },
    {
      "type": {
        "label": "name",
        "beforeExpr": false,
        "startsExpr": true,
        "rightAssociative": false,
        "isLoop": false,
        "isAssign": false,
        "prefix": false,
        "postfix": false,
        "binop": null
      },
      "value": "async",
      "start": 201,
      "end": 206,
      "loc": {
        "start": {
          "line": 14,
          "column": 4
        },
        "end": {
          "line": 14,
          "column": 9
        }
      }
    },
    {
      "type": {
        "label": "name",
        "beforeExpr": false,
        "startsExpr": true,
        "rightAssociative": false,
        "isLoop": false,
        "isAssign": false,
        "prefix": false,
        "postfix": false,
        "binop": null
      },
      "value": "getAllPuppies",
      "start": 207,
      "end": 220,
      "loc": {
        "start": {
          "line": 14,
          "column": 10
        },
        "end": {
          "line": 14,
          "column": 23
        }
      }
    },
    {
      "type": {
        "label": "(",
        "beforeExpr": true,
        "startsExpr": true,
        "rightAssociative": false,
        "isLoop": false,
        "isAssign": false,
        "prefix": false,
        "postfix": false,
        "binop": null
      },
      "start": 220,
      "end": 221,
      "loc": {
        "start": {
          "line": 14,
          "column": 23
        },
        "end": {
          "line": 14,
          "column": 24
        }
      }
    },
    {
      "type": {
        "label": ")",
        "beforeExpr": false,
        "startsExpr": false,
        "rightAssociative": false,
        "isLoop": false,
        "isAssign": false,
        "prefix": false,
        "postfix": false,
        "binop": null
      },
      "start": 221,
      "end": 222,
      "loc": {
        "start": {
          "line": 14,
          "column": 24
        },
        "end": {
          "line": 14,
          "column": 25
        }
      }
    },
    {
      "type": {
        "label": "{",
        "beforeExpr": true,
        "startsExpr": true,
        "rightAssociative": false,
        "isLoop": false,
        "isAssign": false,
        "prefix": false,
        "postfix": false,
        "binop": null
      },
      "start": 223,
      "end": 224,
      "loc": {
        "start": {
          "line": 14,
          "column": 26
        },
        "end": {
          "line": 14,
          "column": 27
        }
      }
    },
    {
      "type": {
        "label": "const",
        "keyword": "const",
        "beforeExpr": false,
        "startsExpr": false,
        "rightAssociative": false,
        "isLoop": false,
        "isAssign": false,
        "prefix": false,
        "postfix": false,
        "binop": null,
        "updateContext": null
      },
      "value": "const",
      "start": 233,
      "end": 238,
      "loc": {
        "start": {
          "line": 15,
          "column": 8
        },
        "end": {
          "line": 15,
          "column": 13
        }
      }
    },
    {
      "type": {
        "label": "name",
        "beforeExpr": false,
        "startsExpr": true,
        "rightAssociative": false,
        "isLoop": false,
        "isAssign": false,
        "prefix": false,
        "postfix": false,
        "binop": null
      },
      "value": "httpResponse",
      "start": 239,
      "end": 251,
      "loc": {
        "start": {
          "line": 15,
          "column": 14
        },
        "end": {
          "line": 15,
          "column": 26
        }
      }
    },
    {
      "type": {
        "label": "=",
        "beforeExpr": true,
        "startsExpr": false,
        "rightAssociative": false,
        "isLoop": false,
        "isAssign": true,
        "prefix": false,
        "postfix": false,
        "binop": null,
        "updateContext": null
      },
      "value": "=",
      "start": 252,
      "end": 253,
      "loc": {
        "start": {
          "line": 15,
          "column": 27
        },
        "end": {
          "line": 15,
          "column": 28
        }
      }
    },
    {
      "type": {
        "label": "name",
        "beforeExpr": false,
        "startsExpr": true,
        "rightAssociative": false,
        "isLoop": false,
        "isAssign": false,
        "prefix": false,
        "postfix": false,
        "binop": null
      },
      "value": "await",
      "start": 254,
      "end": 259,
      "loc": {
        "start": {
          "line": 15,
          "column": 29
        },
        "end": {
          "line": 15,
          "column": 34
        }
      }
    },
    {
      "type": {
        "label": "this",
        "keyword": "this",
        "beforeExpr": false,
        "startsExpr": true,
        "rightAssociative": false,
        "isLoop": false,
        "isAssign": false,
        "prefix": false,
        "postfix": false,
        "binop": null,
        "updateContext": null
      },
      "value": "this",
      "start": 260,
      "end": 264,
      "loc": {
        "start": {
          "line": 15,
          "column": 35
        },
        "end": {
          "line": 15,
          "column": 39
        }
      }
    },
    {
      "type": {
        "label": ".",
        "beforeExpr": false,
        "startsExpr": false,
        "rightAssociative": false,
        "isLoop": false,
        "isAssign": false,
        "prefix": false,
        "postfix": false,
        "binop": null,
        "updateContext": null
      },
      "start": 264,
      "end": 265,
      "loc": {
        "start": {
          "line": 15,
          "column": 39
        },
        "end": {
          "line": 15,
          "column": 40
        }
      }
    },
    {
      "type": {
        "label": "name",
        "beforeExpr": false,
        "startsExpr": true,
        "rightAssociative": false,
        "isLoop": false,
        "isAssign": false,
        "prefix": false,
        "postfix": false,
        "binop": null
      },
      "value": "http",
      "start": 265,
      "end": 269,
      "loc": {
        "start": {
          "line": 15,
          "column": 40
        },
        "end": {
          "line": 15,
          "column": 44
        }
      }
    },
    {
      "type": {
        "label": ".",
        "beforeExpr": false,
        "startsExpr": false,
        "rightAssociative": false,
        "isLoop": false,
        "isAssign": false,
        "prefix": false,
        "postfix": false,
        "binop": null,
        "updateContext": null
      },
      "start": 269,
      "end": 270,
      "loc": {
        "start": {
          "line": 15,
          "column": 44
        },
        "end": {
          "line": 15,
          "column": 45
        }
      }
    },
    {
      "type": {
        "label": "name",
        "beforeExpr": false,
        "startsExpr": true,
        "rightAssociative": false,
        "isLoop": false,
        "isAssign": false,
        "prefix": false,
        "postfix": false,
        "binop": null
      },
      "value": "get",
      "start": 270,
      "end": 273,
      "loc": {
        "start": {
          "line": 15,
          "column": 45
        },
        "end": {
          "line": 15,
          "column": 48
        }
      }
    },
    {
      "type": {
        "label": "(",
        "beforeExpr": true,
        "startsExpr": true,
        "rightAssociative": false,
        "isLoop": false,
        "isAssign": false,
        "prefix": false,
        "postfix": false,
        "binop": null
      },
      "start": 273,
      "end": 274,
      "loc": {
        "start": {
          "line": 15,
          "column": 48
        },
        "end": {
          "line": 15,
          "column": 49
        }
      }
    },
    {
      "type": {
        "label": "string",
        "beforeExpr": false,
        "startsExpr": true,
        "rightAssociative": false,
        "isLoop": false,
        "isAssign": false,
        "prefix": false,
        "postfix": false,
        "binop": null,
        "updateContext": null
      },
      "value": "/puppies",
      "start": 274,
      "end": 284,
      "loc": {
        "start": {
          "line": 15,
          "column": 49
        },
        "end": {
          "line": 15,
          "column": 59
        }
      }
    },
    {
      "type": {
        "label": ")",
        "beforeExpr": false,
        "startsExpr": false,
        "rightAssociative": false,
        "isLoop": false,
        "isAssign": false,
        "prefix": false,
        "postfix": false,
        "binop": null
      },
      "start": 284,
      "end": 285,
      "loc": {
        "start": {
          "line": 15,
          "column": 59
        },
        "end": {
          "line": 15,
          "column": 60
        }
      }
    },
    {
      "type": {
        "label": ";",
        "beforeExpr": true,
        "startsExpr": false,
        "rightAssociative": false,
        "isLoop": false,
        "isAssign": false,
        "prefix": false,
        "postfix": false,
        "binop": null,
        "updateContext": null
      },
      "start": 285,
      "end": 286,
      "loc": {
        "start": {
          "line": 15,
          "column": 60
        },
        "end": {
          "line": 15,
          "column": 61
        }
      }
    },
    {
      "type": {
        "label": "if",
        "keyword": "if",
        "beforeExpr": false,
        "startsExpr": false,
        "rightAssociative": false,
        "isLoop": false,
        "isAssign": false,
        "prefix": false,
        "postfix": false,
        "binop": null,
        "updateContext": null
      },
      "value": "if",
      "start": 295,
      "end": 297,
      "loc": {
        "start": {
          "line": 16,
          "column": 8
        },
        "end": {
          "line": 16,
          "column": 10
        }
      }
    },
    {
      "type": {
        "label": "(",
        "beforeExpr": true,
        "startsExpr": true,
        "rightAssociative": false,
        "isLoop": false,
        "isAssign": false,
        "prefix": false,
        "postfix": false,
        "binop": null
      },
      "start": 297,
      "end": 298,
      "loc": {
        "start": {
          "line": 16,
          "column": 10
        },
        "end": {
          "line": 16,
          "column": 11
        }
      }
    },
    {
      "type": {
        "label": "name",
        "beforeExpr": false,
        "startsExpr": true,
        "rightAssociative": false,
        "isLoop": false,
        "isAssign": false,
        "prefix": false,
        "postfix": false,
        "binop": null
      },
      "value": "httpResponse",
      "start": 298,
      "end": 310,
      "loc": {
        "start": {
          "line": 16,
          "column": 11
        },
        "end": {
          "line": 16,
          "column": 23
        }
      }
    },
    {
      "type": {
        "label": ".",
        "beforeExpr": false,
        "startsExpr": false,
        "rightAssociative": false,
        "isLoop": false,
        "isAssign": false,
        "prefix": false,
        "postfix": false,
        "binop": null,
        "updateContext": null
      },
      "start": 310,
      "end": 311,
      "loc": {
        "start": {
          "line": 16,
          "column": 23
        },
        "end": {
          "line": 16,
          "column": 24
        }
      }
    },
    {
      "type": {
        "label": "name",
        "beforeExpr": false,
        "startsExpr": true,
        "rightAssociative": false,
        "isLoop": false,
        "isAssign": false,
        "prefix": false,
        "postfix": false,
        "binop": null
      },
      "value": "hasError",
      "start": 311,
      "end": 319,
      "loc": {
        "start": {
          "line": 16,
          "column": 24
        },
        "end": {
          "line": 16,
          "column": 32
        }
      }
    },
    {
      "type": {
        "label": "(",
        "beforeExpr": true,
        "startsExpr": true,
        "rightAssociative": false,
        "isLoop": false,
        "isAssign": false,
        "prefix": false,
        "postfix": false,
        "binop": null
      },
      "start": 319,
      "end": 320,
      "loc": {
        "start": {
          "line": 16,
          "column": 32
        },
        "end": {
          "line": 16,
          "column": 33
        }
      }
    },
    {
      "type": {
        "label": ")",
        "beforeExpr": false,
        "startsExpr": false,
        "rightAssociative": false,
        "isLoop": false,
        "isAssign": false,
        "prefix": false,
        "postfix": false,
        "binop": null
      },
      "start": 320,
      "end": 321,
      "loc": {
        "start": {
          "line": 16,
          "column": 33
        },
        "end": {
          "line": 16,
          "column": 34
        }
      }
    },
    {
      "type": {
        "label": ")",
        "beforeExpr": false,
        "startsExpr": false,
        "rightAssociative": false,
        "isLoop": false,
        "isAssign": false,
        "prefix": false,
        "postfix": false,
        "binop": null
      },
      "start": 321,
      "end": 322,
      "loc": {
        "start": {
          "line": 16,
          "column": 34
        },
        "end": {
          "line": 16,
          "column": 35
        }
      }
    },
    {
      "type": {
        "label": "throw",
        "keyword": "throw",
        "beforeExpr": true,
        "startsExpr": false,
        "rightAssociative": false,
        "isLoop": false,
        "isAssign": false,
        "prefix": false,
        "postfix": false,
        "binop": null,
        "updateContext": null
      },
      "value": "throw",
      "start": 323,
      "end": 328,
      "loc": {
        "start": {
          "line": 16,
          "column": 36
        },
        "end": {
          "line": 16,
          "column": 41
        }
      }
    },
    {
      "type": {
        "label": "name",
        "beforeExpr": false,
        "startsExpr": true,
        "rightAssociative": false,
        "isLoop": false,
        "isAssign": false,
        "prefix": false,
        "postfix": false,
        "binop": null
      },
      "value": "httpResponse",
      "start": 329,
      "end": 341,
      "loc": {
        "start": {
          "line": 16,
          "column": 42
        },
        "end": {
          "line": 16,
          "column": 54
        }
      }
    },
    {
      "type": {
        "label": ".",
        "beforeExpr": false,
        "startsExpr": false,
        "rightAssociative": false,
        "isLoop": false,
        "isAssign": false,
        "prefix": false,
        "postfix": false,
        "binop": null,
        "updateContext": null
      },
      "start": 341,
      "end": 342,
      "loc": {
        "start": {
          "line": 16,
          "column": 54
        },
        "end": {
          "line": 16,
          "column": 55
        }
      }
    },
    {
      "type": {
        "label": "name",
        "beforeExpr": false,
        "startsExpr": true,
        "rightAssociative": false,
        "isLoop": false,
        "isAssign": false,
        "prefix": false,
        "postfix": false,
        "binop": null
      },
      "value": "error",
      "start": 342,
      "end": 347,
      "loc": {
        "start": {
          "line": 16,
          "column": 55
        },
        "end": {
          "line": 16,
          "column": 60
        }
      }
    },
    {
      "type": {
        "label": ";",
        "beforeExpr": true,
        "startsExpr": false,
        "rightAssociative": false,
        "isLoop": false,
        "isAssign": false,
        "prefix": false,
        "postfix": false,
        "binop": null,
        "updateContext": null
      },
      "start": 347,
      "end": 348,
      "loc": {
        "start": {
          "line": 16,
          "column": 60
        },
        "end": {
          "line": 16,
          "column": 61
        }
      }
    },
    {
      "type": {
        "label": "return",
        "keyword": "return",
        "beforeExpr": true,
        "startsExpr": false,
        "rightAssociative": false,
        "isLoop": false,
        "isAssign": false,
        "prefix": false,
        "postfix": false,
        "binop": null,
        "updateContext": null
      },
      "value": "return",
      "start": 357,
      "end": 363,
      "loc": {
        "start": {
          "line": 17,
          "column": 8
        },
        "end": {
          "line": 17,
          "column": 14
        }
      }
    },
    {
      "type": {
        "label": "name",
        "beforeExpr": false,
        "startsExpr": true,
        "rightAssociative": false,
        "isLoop": false,
        "isAssign": false,
        "prefix": false,
        "postfix": false,
        "binop": null
      },
      "value": "httpResponse",
      "start": 364,
      "end": 376,
      "loc": {
        "start": {
          "line": 17,
          "column": 15
        },
        "end": {
          "line": 17,
          "column": 27
        }
      }
    },
    {
      "type": {
        "label": ".",
        "beforeExpr": false,
        "startsExpr": false,
        "rightAssociative": false,
        "isLoop": false,
        "isAssign": false,
        "prefix": false,
        "postfix": false,
        "binop": null,
        "updateContext": null
      },
      "start": 376,
      "end": 377,
      "loc": {
        "start": {
          "line": 17,
          "column": 27
        },
        "end": {
          "line": 17,
          "column": 28
        }
      }
    },
    {
      "type": {
        "label": "name",
        "beforeExpr": false,
        "startsExpr": true,
        "rightAssociative": false,
        "isLoop": false,
        "isAssign": false,
        "prefix": false,
        "postfix": false,
        "binop": null
      },
      "value": "response",
      "start": 377,
      "end": 385,
      "loc": {
        "start": {
          "line": 17,
          "column": 28
        },
        "end": {
          "line": 17,
          "column": 36
        }
      }
    },
    {
      "type": {
        "label": ";",
        "beforeExpr": true,
        "startsExpr": false,
        "rightAssociative": false,
        "isLoop": false,
        "isAssign": false,
        "prefix": false,
        "postfix": false,
        "binop": null,
        "updateContext": null
      },
      "start": 385,
      "end": 386,
      "loc": {
        "start": {
          "line": 17,
          "column": 36
        },
        "end": {
          "line": 17,
          "column": 37
        }
      }
    },
    {
      "type": {
        "label": "}",
        "beforeExpr": false,
        "startsExpr": false,
        "rightAssociative": false,
        "isLoop": false,
        "isAssign": false,
        "prefix": false,
        "postfix": false,
        "binop": null
      },
      "start": 391,
      "end": 392,
      "loc": {
        "start": {
          "line": 18,
          "column": 4
        },
        "end": {
          "line": 18,
          "column": 5
        }
      }
    },
    {
      "type": {
        "label": "}",
        "beforeExpr": false,
        "startsExpr": false,
        "rightAssociative": false,
        "isLoop": false,
        "isAssign": false,
        "prefix": false,
        "postfix": false,
        "binop": null
      },
      "start": 393,
      "end": 394,
      "loc": {
        "start": {
          "line": 19,
          "column": 0
        },
        "end": {
          "line": 19,
          "column": 1
        }
      }
    },
    {
      "type": {
        "label": "export",
        "keyword": "export",
        "beforeExpr": false,
        "startsExpr": false,
        "rightAssociative": false,
        "isLoop": false,
        "isAssign": false,
        "prefix": false,
        "postfix": false,
        "binop": null,
        "updateContext": null
      },
      "value": "export",
      "start": 396,
      "end": 402,
      "loc": {
        "start": {
          "line": 21,
          "column": 0
        },
        "end": {
          "line": 21,
          "column": 6
        }
      }
    },
    {
      "type": {
        "label": "default",
        "keyword": "default",
        "beforeExpr": true,
        "startsExpr": false,
        "rightAssociative": false,
        "isLoop": false,
        "isAssign": false,
        "prefix": false,
        "postfix": false,
        "binop": null,
        "updateContext": null
      },
      "value": "default",
      "start": 403,
      "end": 410,
      "loc": {
        "start": {
          "line": 21,
          "column": 7
        },
        "end": {
          "line": 21,
          "column": 14
        }
      }
    },
    {
      "type": {
        "label": "name",
        "beforeExpr": false,
        "startsExpr": true,
        "rightAssociative": false,
        "isLoop": false,
        "isAssign": false,
        "prefix": false,
        "postfix": false,
        "binop": null
      },
      "value": "PuppyApi",
      "start": 411,
      "end": 419,
      "loc": {
        "start": {
          "line": 21,
          "column": 15
        },
        "end": {
          "line": 21,
          "column": 23
        }
      }
    },
    {
      "type": {
        "label": ";",
        "beforeExpr": true,
        "startsExpr": false,
        "rightAssociative": false,
        "isLoop": false,
        "isAssign": false,
        "prefix": false,
        "postfix": false,
        "binop": null,
        "updateContext": null
      },
      "start": 419,
      "end": 420,
      "loc": {
        "start": {
          "line": 21,
          "column": 23
        },
        "end": {
          "line": 21,
          "column": 24
        }
      }
    },
    {
      "type": {
        "label": "eof",
        "beforeExpr": false,
        "startsExpr": false,
        "rightAssociative": false,
        "isLoop": false,
        "isAssign": false,
        "prefix": false,
        "postfix": false,
        "binop": null,
        "updateContext": null
      },
      "start": 421,
      "end": 421,
      "loc": {
        "start": {
          "line": 22,
          "column": 0
        },
        "end": {
          "line": 22,
          "column": 0
        }
      }
    }
  ]
}